callouts/__init__.py
callouts-0.1.0.dist-info/METADATA
callouts-0.1.0.dist-info/WHEEL
callouts-0.1.0.dist-info/top_level.txt
callouts-0.1.0.dist-info/RECORD
