Metadata-Version: 2.1
Name: callouts
Version: 0.1.0
Summary: A simple, class based dispatcher
Home-page: https://github.com/michalporeba/toposearch/packages/dispatcher
Author: Michal Poreba
License: MIT
Platform: UNKNOWN
Classifier: Development Status :: 3 - Alpha
Classifier: License :: OSI Approved :: MIT License
Classifier: Programming Language :: Python :: 3
Classifier: Framework :: Django :: 4.0
Classifier: Intended Audience :: Developers
Classifier: Topic :: Software Development
